_martinez.cp35-win_amd64.pyd
martinez/__init__.py
martinez/boolean.py
martinez/bounding_box.py
martinez/contour.py
martinez/hints.py
martinez/point.py
martinez/polygon.py
martinez/segment.py
martinez/utilities.py
martinez-0.6.0.dist-info/LICENSE
martinez-0.6.0.dist-info/METADATA
martinez-0.6.0.dist-info/WHEEL
martinez-0.6.0.dist-info/top_level.txt
martinez-0.6.0.dist-info/RECORD
