Metadata-Version: 2.1
Name: martinez
Version: 0.6.0
Summary: Python port of polygon clipping algorithm by F. Martinez et al.
Home-page: https://github.com/lycantropos/martinez/
Author: Azat Ibrakov
Author-email: azatibrakov@gmail.com
License: MIT License
Download-URL: https://github.com/lycantropos/martinez/archive/master.zip
Platform: UNKNOWN
Classifier: License :: OSI Approved :: MIT License
Classifier: Programming Language :: Python :: 3.5
Classifier: Programming Language :: Python :: 3.6
Classifier: Programming Language :: Python :: 3.7
Classifier: Programming Language :: Python :: 3.8
Classifier: Programming Language :: Python :: 3.9
Classifier: Programming Language :: Python :: Implementation :: CPython
Classifier: Programming Language :: Python :: Implementation :: PyPy
Requires-Python: >=3.5
